paramlake/__init__.py
paramlake/default_config.yaml
paramlake/collectors/__init__.py
paramlake/collectors/activation_collector.py
paramlake/collectors/gradient_collector.py
paramlake/collectors/weight_collector.py
paramlake/decorators/__init__.py
paramlake/decorators/model_decorator.py
paramlake/schema/__init__.py
paramlake/schema/schema.py
paramlake/storage/__init__.py
paramlake/storage/factory.py
paramlake/storage/icechunk_analyzer.py
paramlake/storage/icechunk_manager.py
paramlake/storage/storage_interface.py
paramlake/storage/zarr_analyzer.py
paramlake/storage/zarr_manager.py
paramlake/utils/__init__.py
paramlake/utils/config.py
paramlake/utils/model_utils.py
paramlake-0.1.1.dist-info/licenses/LICENSE
paramlake-0.1.1.dist-info/METADATA
paramlake-0.1.1.dist-info/WHEEL
paramlake-0.1.1.dist-info/top_level.txt
paramlake-0.1.1.dist-info/RECORD
