Metadata-Version: 2.4
Name: paramlake
Version: 0.1.1
Summary: A comprehensive parameter tracking and storage system for TensorFlow models using Zarr
Author-email: Pranav Sateesh <pranav.sateesh99@gmail.com>
License-Expression: MIT
Project-URL: Homepage, https://github.com/stprnvsh/paramlake
Project-URL: Repository, https://github.com/stprnvsh/paramlake
Requires-Python: >=3.8
License-File: LICENSE
Requires-Dist: tensorflow>=2.6.0
Requires-Dist: zarr>=2.12.0
Requires-Dist: numcodecs>=0.10.0
Requires-Dist: pyyaml>=6.0
Requires-Dist: numpy>=1.19.0
Provides-Extra: dev
Requires-Dist: pytest>=7.0.0; extra == "dev"
Requires-Dist: black>=22.0.0; extra == "dev"
Requires-Dist: isort>=5.10.0; extra == "dev"
Requires-Dist: mypy>=0.950; extra == "dev"
Provides-Extra: visualize
Requires-Dist: matplotlib>=3.5.0; extra == "visualize"
Requires-Dist: seaborn>=0.11.0; extra == "visualize"
Dynamic: license-file
